{"fileName":"output7.json","config":{"edgesNumberDistribution":{"n":8,"distributionType":"org.qesm.app.model.generator.distribution.SingleValueDistribution"},"edgesLocalityDistribution":{"min":-4,"max":4,"distributionType":"org.qesm.app.model.generator.distribution.UniformDistribution"},"selfLoopValue":null,"seed":1884628528,"statisticalTestConfig":{"confidence":0.95,"error":0.01,"testClass":"org.qesm.app.model.test.ZTest"},"connectSCCs":false,"description":"","pythonHistogramImage":true,"pythonLastSequenceImage":false,"n":16},"perfectSamplingOutput":{"avgSteps":31.535278,"sigma":18.29150464648372,"distance":4.7239181770527416E-4,"statisticalTest":{"name":"ZTest","confidence":0.95,"maxError":0.01,"currentError":0.009999281313220735,"samplesSize":12926,"stdDev":18.291504646483684,"mean":31.535277734798083}},"dumbSamplingOutputs":[{"sigmas":0,"steps":32,"distance":5.163988978278735E-4},{"sigmas":1,"steps":50,"distance":4.5381022917714126E-4},{"sigmas":2,"steps":68,"distance":5.269530060909718E-4}]}